riprint/__init__.py
riprint-1.0.5.dist-info/LICENSE.txt
riprint-1.0.5.dist-info/METADATA
riprint-1.0.5.dist-info/WHEEL
riprint-1.0.5.dist-info/top_level.txt
riprint-1.0.5.dist-info/RECORD
