Metadata-Version: 2.1
Name: riprint
Version: 1.0.5
Home-page: https://github.com/Reddan/riprint
Author: Hampus Hallman
Author-email: me@hampushallman.com
License: MIT
Requires-Python: ~=3.5
License-File: LICENSE.txt
Requires-Dist: numpy
Requires-Dist: termcolor
